spinnman/__init__.py
spinnman/_version.py
spinnman/board_test_configuration.py
spinnman/config_setup.py
spinnman/constants.py
spinnman/exceptions.py
spinnman/get_cores_in_run_state.py
spinnman/py.typed
spinnman/spinnman.cfg
spinnman/spinnman_script.py
spinnman/spinnman_simulation.py
spinnman/connections/__init__.py
spinnman/connections/connection_listener.py
spinnman/connections/scp_request_pipeline.py
spinnman/connections/token_bucket.py
spinnman/connections/abstract_classes/__init__.py
spinnman/connections/abstract_classes/abstract_scp_connection.py
spinnman/connections/abstract_classes/connection.py
spinnman/connections/abstract_classes/listenable.py
spinnman/connections/udp_packet_connections/__init__.py
spinnman/connections/udp_packet_connections/bmp_connection.py
spinnman/connections/udp_packet_connections/boot_connection.py
spinnman/connections/udp_packet_connections/eieio_connection.py
spinnman/connections/udp_packet_connections/ip_address_connection.py
spinnman/connections/udp_packet_connections/scamp_connection.py
spinnman/connections/udp_packet_connections/sdp_connection.py
spinnman/connections/udp_packet_connections/udp_connection.py
spinnman/connections/udp_packet_connections/utils.py
spinnman/data/__init__.py
spinnman/data/spinnman_data_view.py
spinnman/data/spinnman_data_writer.py
spinnman/extended/__init__.py
spinnman/extended/bmp_set_led.py
spinnman/extended/de_alloc_sdram_process.py
spinnman/extended/extended_transceiver.py
spinnman/extended/read_adc.py
spinnman/extended/set_led.py
spinnman/extended/version3transceiver.py
spinnman/extended/version5transceiver.py
spinnman/extended/write_memory_flood_process.py
spinnman/messages/__init__.py
spinnman/messages/multicast_message.py
spinnman/messages/eieio/__init__.py
spinnman/messages/eieio/create_eieio_command.py
spinnman/messages/eieio/create_eieio_data.py
spinnman/messages/eieio/eieio_message.py
spinnman/messages/eieio/eieio_prefix.py
spinnman/messages/eieio/eieio_type.py
spinnman-1!7.4.0.dist-info/licenses/LICENSE
spinnman-1!7.4.0.dist-info/licenses/LICENSE_POLICY.md
spinnman-1!7.4.0.dist-info/METADATA
spinnman-1!7.4.0.dist-info/WHEEL
spinnman-1!7.4.0.dist-info/entry_points.txt
spinnman-1!7.4.0.dist-info/top_level.txt
spinnman-1!7.4.0.dist-info/zip-safe
spinnman-1!7.4.0.dist-info/RECORD
