Metadata-Version: 2.4
Name: SpiNNMan
Version: 1!7.4.0
Summary: Interaction with a SpiNNaker Machine
Home-page: https://github.com/SpiNNakerManchester/SpiNNMan
Maintainer: SpiNNakerTeam
Maintainer-email: spinnakerusers@googlegroups.com
License: Apache-2.0
Keywords: spinnaker,machine interface
Classifier: Development Status :: 5 - Production/Stable
Classifier: Intended Audience :: Developers
Classifier: Intended Audience :: Science/Research
Classifier: Natural Language :: English
Classifier: Operating System :: POSIX :: Linux
Classifier: Operating System :: Microsoft :: Windows
Classifier: Operating System :: MacOS
Classifier: Programming Language :: Python :: 3
Classifier: Programming Language :: Python :: 3.8
Classifier: Programming Language :: Python :: 3.9
Classifier: Programming Language :: Python :: 3.10
Classifier: Programming Language :: Python :: 3.11
Classifier: Programming Language :: Python :: 3.12
Classifier: Programming Language :: Python :: 3.13
Requires-Python: !=3.13.6,<4,>=3.8
License-File: LICENSE
License-File: LICENSE_POLICY.md
Requires-Dist: SpiNNMachine==1!7.4.0
Requires-Dist: matplotlib
Requires-Dist: websocket-client
Requires-Dist: ebrains_drive>=0.5.1
Provides-Extra: test
Requires-Dist: pytest-cov; extra == "test"
Requires-Dist: testfixtures; extra == "test"
Requires-Dist: httpretty!=1.0.0; extra == "test"
Requires-Dist: types-requests; extra == "test"
Dynamic: license-file
